pongy/__init__.py
pongy/client/__init__.py
pongy/client/app.py
pongy/client/connection.py
pongy/client/controls.py
pongy/client/ui.py
pongy/client/widgets/__init__.py
pongy/client/widgets/ball.py
pongy/client/widgets/racket.py
pongy/client/widgets/score.py
pongy/models.py
pongy/server/__init__.py
pongy/server/app.py
pongy/server/ball.py
pongy/server/game.py
pongy/server/player.py
pongy/server/racket.py
pongy/settings.py
run.py
pongy-0.4.1.dist-info/entry_points.txt
pongy-0.4.1.dist-info/LICENSE
pongy-0.4.1.dist-info/WHEEL
pongy-0.4.1.dist-info/METADATA
pongy-0.4.1.dist-info/RECORD
